LICENSE
MANIFEST.in
README.md
setup.cfg
setup.py
datetimepicker/__init__.py
datetimepicker/helpers.py
datetimepicker/urls.py
datetimepicker/views.py
datetimepicker/widgets.py
django_inawrath_datetimepicker.egg-info/PKG-INFO
django_inawrath_datetimepicker.egg-info/SOURCES.txt
django_inawrath_datetimepicker.egg-info/dependency_links.txt
django_inawrath_datetimepicker.egg-info/top_level.txt