Metadata-Version: 1.1
Name: django-inawrath-datetimepicker
Version: 3.0
Summary: Datetimepicker for Django projects.
Home-page: https://github.com/inawrath/django-datetimepicker.git
Author: Pablo Escodebar
Author-email: inawrathc@gmail.com
License: Apache License 2.0
Platform: UNKNOWN
Classifier: Intended Audience :: Developers
Classifier: License :: OSI Approved :: Apache Software License
Classifier: Programming Language :: Python
Classifier: Programming Language :: Python :: 3
Classifier: Operating System :: OS Independent
Classifier: Topic :: Software Development :: Libraries
Classifier: Topic :: Utilities
Classifier: Environment :: Web Environment
Classifier: Framework :: Django
